fw_ddsm/__init__.py
fw_ddsm/aggregator.py
fw_ddsm/community.py
fw_ddsm/household.py
fw_ddsm/iteration.py
fw_ddsm/output.py
fw_ddsm/parameter.py
fw_ddsm/tracker.py
fw_ddsm/scripts/__init__.py
fw_ddsm/scripts/aggregator_generation.py
fw_ddsm/scripts/aggregator_pricing.py
fw_ddsm/scripts/custom_functions.py
fw_ddsm/scripts/household_generation.py
fw_ddsm/scripts/household_scheduling.py
fw_ddsm-0.10.8.dist-info/LICENSE
fw_ddsm-0.10.8.dist-info/METADATA
fw_ddsm-0.10.8.dist-info/WHEEL
fw_ddsm-0.10.8.dist-info/top_level.txt
fw_ddsm-0.10.8.dist-info/RECORD
