Metadata-Version: 2.1
Name: fw-ddsm
Version: 0.10.8
Summary: Frank-Wolfe-based distributed demand scheduling method package
Home-page: https://github.com/dorahee/FW-DDSM.git
Author: Shan Dora He
Author-email: dora.shan.he@gmail.com
License: UNKNOWN
Platform: UNKNOWN
Classifier: Programming Language :: Python :: 3
Classifier: License :: OSI Approved :: GNU General Public License v3 or later (GPLv3+)
Classifier: Operating System :: OS Independent
Requires-Python: >=3.6
